ec2stash/__init__.py
ec2stash/cli.py
ec2stash/core.py
ec2stash-0.1.4.dist-info/DESCRIPTION.rst
ec2stash-0.1.4.dist-info/METADATA
ec2stash-0.1.4.dist-info/RECORD
ec2stash-0.1.4.dist-info/WHEEL
ec2stash-0.1.4.dist-info/entry_points.txt
ec2stash-0.1.4.dist-info/metadata.json
ec2stash-0.1.4.dist-info/top_level.txt
