Metadata-Version: 2.0
Name: ec2stash
Version: 0.1.4
Summary: EC2 stash using AWS Parameters Store
Home-page: https://github.com/giuliocalzolari/ec2stash
Author: giuliocalzolari
Author-email: gc@hide.me
License: MIT
Keywords: ec2stash
Platform: UNKNOWN
Classifier: Development Status :: 5 - Production/Stable
Classifier: Intended Audience :: Developers
Classifier: Natural Language :: English
Classifier: Environment :: Console
Classifier: Programming Language :: Python :: 2
Classifier: Programming Language :: Python :: 2.6
Classifier: Programming Language :: Python :: 2.7
Requires-Dist: boto3 (>=1.3.0)
Requires-Dist: click (>=6.6)
Requires-Dist: packaging (>=16.8)
